<?xml version="1.0" encoding="UTF-8"?>
<?xml-stylesheet type="text/xsl" href="treegross.xsl"?><Bestand><Id>1</Id><Kennung>Generated Stand</Kennung><Allgemeines> </Allgemeines><Flaechengroesse_m2>200.0</Flaechengroesse_m2><HauptbaumArtCodeStd>211</HauptbaumArtCodeStd><HauptbaumArtCodeLokal>211</HauptbaumArtCodeLokal><AufnahmeJahr>2008</AufnahmeJahr><AufnahmeMonat>3</AufnahmeMonat><DatenHerkunft></DatenHerkunft><Standort></Standort><Hochwert_m>0.0</Hochwert_m><Rechtswert_m>0.0</Rechtswert_m><Hoehe_uNN_m>-99.9</Hoehe_uNN_m><Exposition_Gon>-99</Exposition_Gon><Hangneigung_Prozent>-99.9</Hangneigung_Prozent><Wuchsgebiet></Wuchsgebiet><Wuchsbezirk></Wuchsbezirk><Standortskennziffer></Standortskennziffer><Baumartencode><Code>211</Code><deutscherName>Buche</deutscherName><lateinischerName>Fagus silvatica http://de.wikipedia.org/wiki/Rotbuche</lateinischerName></Baumartencode><Eckpunkt><Nr>polygon</Nr><RelativeXKoordinate_m>7.07</RelativeXKoordinate_m><RelativeYKoordinate_m>7.07</RelativeYKoordinate_m><RelativeBodenhoehe_m>0.00</RelativeBodenhoehe_m></Eckpunkt><Eckpunkt><Nr>ECK1</Nr><RelativeXKoordinate_m>0.00</RelativeXKoordinate_m><RelativeYKoordinate_m>0.00</RelativeYKoordinate_m><RelativeBodenhoehe_m>0.00</RelativeBodenhoehe_m></Eckpunkt><Eckpunkt><Nr>ECK2</Nr><RelativeXKoordinate_m>0.00</RelativeXKoordinate_m><RelativeYKoordinate_m>14.14</RelativeYKoordinate_m><RelativeBodenhoehe_m>0.00</RelativeBodenhoehe_m></Eckpunkt><Eckpunkt><Nr>ECK3</Nr><RelativeXKoordinate_m>14.14</RelativeXKoordinate_m><RelativeYKoordinate_m>14.14</RelativeYKoordinate_m><RelativeBodenhoehe_m>0.00</RelativeBodenhoehe_m></Eckpunkt><Eckpunkt><Nr>ECK4</Nr><RelativeXKoordinate_m>14.14</RelativeXKoordinate_m><RelativeYKoordinate_m>0.00</RelativeYKoordinate_m><RelativeBodenhoehe_m>0.00</RelativeBodenhoehe_m></Eckpunkt><Baum><Nr>1</Nr><Kennung>1</Kennung><BaumartcodeStd>0</BaumartcodeStd><BaumartcodeLokal>211</BaumartcodeLokal><Alter_Jahr>150</Alter_Jahr><BHD_mR_cm>60.00</BHD_mR_cm><Hoehe_m>35.00</Hoehe_m><Kronenansatz_m>17.51</Kronenansatz_m><MittlererKronenDurchmesser_m>11.08</MittlererKronenDurchmesser_m><SiteIndex_m>29.04</SiteIndex_m><RelativeXKoordinate_m>5.22</RelativeXKoordinate_m><RelativeYKoordinate_m>9.22</RelativeYKoordinate_m><RelativeBodenhoehe_m>0.00</RelativeBodenhoehe_m><Lebend>false</Lebend><Entnommen>true</Entnommen><AusscheideMonat>3</AusscheideMonat><AusscheideJahr>2008</AusscheideJahr><AusscheideGrund>Durchforstung</AusscheideGrund><ZBaum>false</ZBaum><ZBaumtemporaer>false</ZBaumtemporaer><HabitatBaum>false</HabitatBaum><KraftscheKlasse>0</KraftscheKlasse><Schicht>0</Schicht><Flaechenfaktor>1.0000</Flaechenfaktor><Volumen_cbm>5.0602</Volumen_cbm><VolumenTotholz_cbm>0.0000</VolumenTotholz_cbm><Bemerkung></Bemerkung></Baum><Baum><Nr>2</Nr><Kennung>2</Kennung><BaumartcodeStd>0</BaumartcodeStd><BaumartcodeLokal>211</BaumartcodeLokal><Alter_Jahr>150</Alter_Jahr><BHD_mR_cm>60.00</BHD_mR_cm><Hoehe_m>35.00</Hoehe_m><Kronenansatz_m>17.51</Kronenansatz_m><MittlererKronenDurchmesser_m>11.08</MittlererKronenDurchmesser_m><SiteIndex_m>29.04</SiteIndex_m><RelativeXKoordinate_m>13.07</RelativeXKoordinate_m><RelativeYKoordinate_m>4.84</RelativeYKoordinate_m><RelativeBodenhoehe_m>0.00</RelativeBodenhoehe_m><Lebend>true</Lebend><Entnommen>false</Entnommen><AusscheideMonat>3</AusscheideMonat><AusscheideJahr>-1</AusscheideJahr><AusscheideGrund></AusscheideGrund><ZBaum>false</ZBaum><ZBaumtemporaer>false</ZBaumtemporaer><HabitatBaum>false</HabitatBaum><KraftscheKlasse>0</KraftscheKlasse><Schicht>0</Schicht><Flaechenfaktor>1.0000</Flaechenfaktor><Volumen_cbm>5.0602</Volumen_cbm><VolumenTotholz_cbm>0.0000</VolumenTotholz_cbm><Bemerkung></Bemerkung></Baum></Bestand>
